lagc/__init__.py
lagc/cli.py
lagc/main.py
lagc/py.typed
lagc/analysis/__init__.py
lagc/analysis/syndrome.py
lagc/core/__init__.py
lagc/core/graph_engine.py
lagc/core/recovery.py
lagc/core/rhg_lattice.py
lagc/core/tensor_slicer.py
lagc/models/__init__.py
lagc/models/hardware.py
lagc/models/topologies.py
lagc/simulation/__init__.py
lagc/simulation/contraction.py
lagc/simulation/scheduler.py
lagc/utils/__init__.py
lagc/utils/memory.py
lagc/utils/visualization.py
lagc_quantum_photonics-1.1.5.dist-info/METADATA
lagc_quantum_photonics-1.1.5.dist-info/WHEEL
lagc_quantum_photonics-1.1.5.dist-info/entry_points.txt
lagc_quantum_photonics-1.1.5.dist-info/top_level.txt
lagc_quantum_photonics-1.1.5.dist-info/RECORD
