Metadata-Version: 2.4
Name: lagc-quantum-photonics
Version: 1.1.5
Summary: LossAware-GraphCompiler: CPU-only loss-aware quantum graph compiler for photonic quantum computing simulation
Author-email: LAGC Research Team <lagc@quantum-photonics.dev>
Maintainer-email: LAGC Research Team <lagc@quantum-photonics.dev>
Project-URL: Homepage, https://github.com/quantum-dev/lagc
Project-URL: Documentation, https://lagc.readthedocs.io
Project-URL: Repository, https://github.com/quantum-dev/lagc
Project-URL: Changelog, https://github.com/quantum-dev/lagc/blob/main/CHANGELOG.md
Project-URL: Bug Tracker, https://github.com/quantum-dev/lagc/issues
Keywords: quantum computing,photonic quantum,graph state,cluster state,tensor network,loss tolerance,MBQC,measurement-based,fault-tolerant,simulation
Classifier: Development Status :: 4 - Beta
Classifier: Intended Audience :: Science/Research
Classifier: Intended Audience :: Developers
Classifier: License :: OSI Approved :: MIT License
Classifier: Operating System :: OS Independent
Classifier: Programming Language :: Python :: 3
Classifier: Programming Language :: Python :: 3.9
Classifier: Programming Language :: Python :: 3.10
Classifier: Programming Language :: Python :: 3.11
Classifier: Programming Language :: Python :: 3.12
Classifier: Topic :: Scientific/Engineering :: Physics
Classifier: Topic :: Scientific/Engineering :: Mathematics
Classifier: Typing :: Typed
Requires-Python: >=3.9
Requires-Dist: numpy>=1.21.0
Requires-Dist: scipy>=1.7.0
Requires-Dist: opt-einsum>=3.3.0
Requires-Dist: networkx>=2.6.0
Provides-Extra: dev
Requires-Dist: pytest>=7.0.0; extra == "dev"
Requires-Dist: pytest-cov>=4.0.0; extra == "dev"
Requires-Dist: black>=23.0.0; extra == "dev"
Requires-Dist: isort>=5.12.0; extra == "dev"
Requires-Dist: mypy>=1.0.0; extra == "dev"
Requires-Dist: flake8>=6.0.0; extra == "dev"
Requires-Dist: pre-commit>=3.0.0; extra == "dev"
Provides-Extra: viz
Requires-Dist: matplotlib>=3.5.0; extra == "viz"
Requires-Dist: plotly>=5.10.0; extra == "viz"
Provides-Extra: docs
Requires-Dist: sphinx>=6.0.0; extra == "docs"
Requires-Dist: sphinx-rtd-theme>=1.0.0; extra == "docs"
Requires-Dist: myst-parser>=1.0.0; extra == "docs"
Provides-Extra: all
Requires-Dist: lagc[dev,docs,viz]; extra == "all"
